{
	"variables": [],
	"info": {
		"name": "Todo",
		"_postman_id": "50d30f01-414d-9262-4839-1fa9214815bb",
		"description": "",
		"schema": "https://schema.getpostman.com/json/collection/v2.0.0/collection.json"
	},
	"item": [
		{
			"name": "Todo",
			"request": {
				"url": "http://localhost:3000/todo",
				"method": "GET",
				"header": [],
				"body": {},
				"description": ""
			},
			"response": []
		},
		{
			"name": "Todo",
			"request": {
				"url": "http://localhost:3000/todo",
				"method": "POST",
				"header": [],
				"body": {
					"mode": "raw",
					"raw": "{\n  \"description\": \"Something here\"\n}"
				},
				"description": ""
			},
			"response": []
		},
		{
			"name": "Todo",
			"request": {
				"url": {
					"raw": "http://localhost:3000/todo/:id",
					"protocol": "http",
					"host": [
						"localhost"
					],
					"port": "3000",
					"path": [
						"todo",
						":id"
					],
					"query": [],
					"variable": [
						{
							"key": "id",
							"value": ""
						}
					]
				},
				"method": "PUT",
				"header": [],
				"body": {},
				"description": ""
			},
			"response": []
		},
		{
			"name": "Todo",
			"request": {
				"url": {
					"raw": "http://localhost:3000/todo/:id",
					"protocol": "http",
					"host": [
						"localhost"
					],
					"port": "3000",
					"path": [
						"todo",
						":id"
					],
					"query": [],
					"variable": [
						{
							"key": "id",
							"value": ""
						}
					]
				},
				"method": "DELETE",
				"header": [],
				"body": {
					"mode": "formdata",
					"formdata": [
						{
							"key": "id",
							"value": "a68b0cd3-55bc-4d27-8e5e-d4109d4972d8",
							"description": "",
							"type": "text"
						}
					]
				},
				"description": ""
			},
			"response": []
		}
	]
}
